{
  "date": "2023-12-02T00:00:00",
  "appointmentType": 1,
  "checkoutStatus": 3,
  "animalName": "Fred 981020053419191",
  "animalNumber": "24-4613",
  "species": "Cat",
  "sex": "Male",
  "ageYears": 0,
  "ageMonths": 2.0,
  "breed": "Domestic Short Hair",
  "isMixed": true,
  "primaryColor": "Brown Tabby",
  "secondaryColor": "With White",
  "microchipProvider": "PetLink",
  "microchipNumber": "981020053419191",
  "spayedNeutered": 1,
  "animalType": "Community Cat (Feral)",
  "ownerFirstName": "Toni",
  "ownerLastName": "Price",
  "ownerCellPhone": "4152613680",
  "ownerHomePhone": null,
  "ownerAddressLine1": "660 Cherry St",
  "ownerAddressLine2": null,
  "ownerCity": "Novato",
  "ownerState": "CA",
  "ownerZip": "94945",
  "trapperFirstName": null,
  "trapperLastName": null,
  "colonyAddressLine1": null,
  "colonyAddressLine2": null,
  "colonyCity": null,
  "colonyState": null,
  "colonyZip": null
}
